drf_yasg/__init__.py
drf_yasg/app_settings.py
drf_yasg/codecs.py
drf_yasg/errors.py
drf_yasg/generators.py
drf_yasg/middleware.py
drf_yasg/openapi.py
drf_yasg/renderers.py
drf_yasg/utils.py
drf_yasg/views.py
drf_yasg/inspectors/__init__.py
drf_yasg/inspectors/base.py
drf_yasg/inspectors/field.py
drf_yasg/inspectors/query.py
drf_yasg/inspectors/view.py
drf_yasg/management/__init__.py
drf_yasg/management/commands/__init__.py
drf_yasg/management/commands/generate_swagger.py
drf_yasg/static/drf-yasg/README
drf_yasg/static/drf-yasg/immutable.js
drf_yasg/static/drf-yasg/immutable.min.js
drf_yasg/static/drf-yasg/insQ.js
drf_yasg/static/drf-yasg/insQ.min.js
drf_yasg/static/drf-yasg/redoc-init.js
drf_yasg/static/drf-yasg/style.css
drf_yasg/static/drf-yasg/swagger-ui-init.js
drf_yasg/static/drf-yasg/redoc/LICENSE
drf_yasg/static/drf-yasg/redoc/redoc-logo.png
drf_yasg/static/drf-yasg/redoc/redoc.min.js
drf_yasg/static/drf-yasg/redoc/redoc.standalone.js.map
drf_yasg/static/drf-yasg/redoc-old/LICENSE
drf_yasg/static/drf-yasg/redoc-old/redoc.min.js
drf_yasg/static/drf-yasg/redoc-old/redoc.min.js.map
drf_yasg/static/drf-yasg/swagger-ui-dist/LICENSE
drf_yasg/static/drf-yasg/swagger-ui-dist/NOTICE
drf_yasg/static/drf-yasg/swagger-ui-dist/absolute-path.js
drf_yasg/static/drf-yasg/swagger-ui-dist/favicon-32x32.png
drf_yasg/static/drf-yasg/swagger-ui-dist/index.css
drf_yasg/static/drf-yasg/swagger-ui-dist/index.js
drf_yasg/static/drf-yasg/swagger-ui-dist/oauth2-redirect.html
drf_yasg/static/drf-yasg/swagger-ui-dist/oauth2-redirect.js
drf_yasg/static/drf-yasg/swagger-ui-dist/swagger-initializer.js
drf_yasg/static/drf-yasg/swagger-ui-dist/swagger-ui-bundle.js
drf_yasg/static/drf-yasg/swagger-ui-dist/swagger-ui-es-bundle-core.js
drf_yasg/static/drf-yasg/swagger-ui-dist/swagger-ui-es-bundle.js
drf_yasg/static/drf-yasg/swagger-ui-dist/swagger-ui-standalone-preset.js
drf_yasg/static/drf-yasg/swagger-ui-dist/swagger-ui.css
drf_yasg/templates/drf-yasg/redoc-old.html
drf_yasg-1.21.13.dist-info/licenses/LICENSE.rst
drf_yasg-1.21.13.dist-info/METADATA
drf_yasg-1.21.13.dist-info/WHEEL
drf_yasg-1.21.13.dist-info/top_level.txt
drf_yasg-1.21.13.dist-info/RECORD
