Metadata-Version: 2.4
Name: drf-yasg
Version: 1.21.13
Summary: Automated generation of real Swagger/OpenAPI 2.0 schemas from Django Rest Framework code.
Author-email: "Cristi V." <cristi@cvjd.me>
License-Expression: BSD-3-Clause
Project-URL: Changelog, https://drf-yasg.readthedocs.io/en/stable/changelog.html
Project-URL: Documentation, https://drf-yasg.readthedocs.io/en/stable/
Project-URL: Homepage, https://github.com/axnsan12/drf-yasg
Project-URL: Issues, https://github.com/axnsan12/drf-yasg/issues
Project-URL: Repository, https://github.com/axnsan12/drf-yasg
Keywords: codegen,django,django-rest-framework,django-rest-swagger,documentation,drf,drf-openapi,drf-yasg,openapi,schema,swagger,swagger-codegen
Classifier: Development Status :: 5 - Production/Stable
Classifier: Environment :: Web Environment
Classifier: Framework :: Django
Classifier: Framework :: Django :: 4.0
Classifier: Framework :: Django :: 4.1
Classifier: Framework :: Django :: 4.2
Classifier: Framework :: Django :: 5.0
Classifier: Framework :: Django :: 5.1
Classifier: Framework :: Django :: 5.2
Classifier: Intended Audience :: Developers
Classifier: Operating System :: OS Independent
Classifier: Programming Language :: Python
Classifier: Programming Language :: Python :: 3
Classifier: Programming Language :: Python :: 3.9
Classifier: Programming Language :: Python :: 3.10
Classifier: Programming Language :: Python :: 3.11
Classifier: Programming Language :: Python :: 3.12
Classifier: Programming Language :: Python :: 3.13
Classifier: Programming Language :: Python :: 3 :: Only
Classifier: Topic :: Documentation
Classifier: Topic :: Software Development :: Code Generators
Requires-Python: >=3.9
License-File: LICENSE.rst
Requires-Dist: django>=4.0
Requires-Dist: djangorestframework>=3.13
Requires-Dist: inflection>=0.3.1
Requires-Dist: packaging>=21.0
Requires-Dist: pytz>=2021.1
Requires-Dist: pyyaml>=5.1
Requires-Dist: uritemplate>=3.0.0
Provides-Extra: coreapi
Requires-Dist: coreapi>=2.3.3; extra == "coreapi"
Requires-Dist: coreschema>=0.0.4; extra == "coreapi"
Provides-Extra: validation
Requires-Dist: swagger-spec-validator>=2.1.0; extra == "validation"
Dynamic: license-file
